typecheck_runner/__init__.py
typecheck_runner/__main__.py
typecheck_runner/py.typed
typecheck_runner/typecheck_runner.py
typecheck_runner-0.1.5.dist-info/licenses/LICENSE
typecheck_runner-0.1.5.dist-info/WHEEL
typecheck_runner-0.1.5.dist-info/entry_points.txt
typecheck_runner-0.1.5.dist-info/METADATA
typecheck_runner-0.1.5.dist-info/RECORD
