Metadata-Version: 2.4
Name: typecheck-runner
Version: 0.1.5
Summary: Unified api to multiple typecheckers
Keywords: typecheck-runner
Author: William P. Krekelberg
Author-email: William P. Krekelberg <wpk@nist.gov>
License-Expression: NIST-PD
License-File: LICENSE
Classifier: Development Status :: 2 - Pre-Alpha
Classifier: Operating System :: OS Independent
Classifier: Programming Language :: Python
Classifier: Programming Language :: Python :: 3 :: Only
Classifier: Programming Language :: Python :: 3.10
Classifier: Programming Language :: Python :: 3.11
Classifier: Programming Language :: Python :: 3.12
Classifier: Programming Language :: Python :: 3.13
Classifier: Programming Language :: Python :: 3.14
Classifier: Programming Language :: Python :: Implementation :: CPython
Classifier: Programming Language :: Python :: Implementation :: PyPy
Classifier: Topic :: Utilities
Classifier: Typing :: Typed
Requires-Dist: packaging>=25.0
Requires-Python: >=3.10
Project-URL: Homepage, https://github.com/wpk-nist-gov/typecheck-runner
